zerisfetch/__init__.py
zerisfetch/main.py
zerisfetch-2.0.0.dist-info/METADATA
zerisfetch-2.0.0.dist-info/WHEEL
zerisfetch-2.0.0.dist-info/entry_points.txt
zerisfetch-2.0.0.dist-info/top_level.txt
zerisfetch-2.0.0.dist-info/RECORD
