Metadata-Version: 2.4
Name: zerisfetch
Version: 2.0.0
Summary: A neofetch-like system information display tool
Home-page: https://github.com/lqq0161-sys/zerisfetch
Author: Zeris Nik
Author-email: Zerisfetch@gmail.com
Project-URL: Bug Reports, https://github.com/lqq0161-sys/zerisfetch/issues
Project-URL: Source, https://github.com/lqq0161-sys/zerisfetch
Keywords: system info neofetch linux debian ubuntu arch
Classifier: Development Status :: 4 - Beta
Classifier: Intended Audience :: End Users/Desktop
Classifier: License :: OSI Approved :: MIT License
Classifier: Operating System :: POSIX :: Linux
Classifier: Programming Language :: Python :: 3
Classifier: Topic :: System :: Systems Administration
Classifier: Topic :: Utilities
Requires-Python: >=3.7
Dynamic: author
Dynamic: author-email
Dynamic: classifier
Dynamic: description
Dynamic: description-content-type
Dynamic: home-page
Dynamic: keywords
Dynamic: project-url
Dynamic: requires-python
Dynamic: summary
